{
  "__inputs": [
    {
      "name": "DS_PROMETHEUS",
      "label": "Prometheus",
      "description": "",
      "type": "datasource",
      "pluginId": "prometheus",
      "pluginName": "Prometheus"
    },
    {
      "name": "VAR_APPLICATION",
      "type": "constant",
      "label": "application",
      "value": "wakatime-sync-server",
      "description": ""
    },
    {
      "name": "VAR_INSTANCE",
      "type": "constant",
      "label": "Instance",
      "value": "192.168.1.17:9090",
      "description": ""
    }
  ],
  "__elements": {},
  "__requires": [
    {
      "type": "panel",
      "id": "gauge",
      "name": "Gauge",
      "version": ""
    },
    {
      "type": "grafana",
      "id": "grafana",
      "name": "Grafana",
      "version": "10.2.0"
    },
    {
      "type": "panel",
      "id": "graph",
      "name": "Graph (old)",
      "version": ""
    },
    {
      "type": "datasource",
      "id": "prometheus",
      "name": "Prometheus",
      "version": "1.0.0"
    },
    {
      "type": "panel",
      "id": "stat",
      "name": "Stat",
      "version": ""
    },
    {
      "type": "panel",
      "id": "timeseries",
      "name": "Time series",
      "version": ""
    }
  ],
  "annotations": {
    "list": [
      {
        "builtIn": 1,
        "datasource": {
          "type": "grafana",
          "uid": "-- Grafana --"
        },
        "enable": true,
        "hide": true,
        "iconColor": "rgba(0, 211, 255, 1)",
        "name": "Annotations & Alerts",
        "target": {
          "limit": 100,
          "matchAny": false,
          "tags": [],
          "type": "dashboard"
        },
        "type": "dashboard"
      }
    ]
  },
  "editable": true,
  "fiscalYearStartMonth": 0,
  "graphTooltip": 0,
  "id": null,
  "links": [],
  "liveNow": false,
  "panels": [
    {
      "collapsed": false,
      "gridPos": {
        "h": 1,
        "w": 24,
        "x": 0,
        "y": 0
      },
      "id": 44,
      "panels": [],
      "title": "wakatime-sync-server业务指标",
      "type": "row"
    },
    {
      "datasource": {
        "type": "prometheus",
        "uid": "${DS_PROMETHEUS}"
      },
      "fieldConfig": {
        "defaults": {
          "color": {
            "mode": "palette-classic"
          },
          "custom": {
            "axisBorderShow": false,
            "axisCenteredZero": false,
            "axisColorMode": "text",
            "axisLabel": "",
            "axisPlacement": "auto",
            "barAlignment": 0,
            "drawStyle": "line",
            "fillOpacity": 0,
            "gradientMode": "none",
            "hideFrom": {
              "legend": false,
              "tooltip": false,
              "viz": false
            },
            "insertNulls": false,
            "lineInterpolation": "linear",
            "lineWidth": 1,
            "pointSize": 5,
            "scaleDistribution": {
              "type": "linear"
            },
            "showPoints": "auto",
            "spanNulls": false,
            "stacking": {
              "group": "A",
              "mode": "none"
            },
            "thresholdsStyle": {
              "mode": "off"
            }
          },
          "mappings": [],
          "thresholds": {
            "mode": "absolute",
            "steps": [
              {
                "color": "green",
                "value": null
              },
              {
                "color": "red",
                "value": 80
              }
            ]
          }
        },
        "overrides": []
      },
      "gridPos": {
        "h": 8,
        "w": 12,
        "x": 0,
        "y": 1
      },
      "id": 46,
      "options": {
        "legend": {
          "calcs": [],
          "displayMode": "list",
          "placement": "bottom",
          "showLegend": true
        },
        "tooltip": {
          "mode": "single",
          "sort": "none"
        }
      },
      "targets": [
        {
          "datasource": {
            "type": "prometheus",
            "uid": "${DS_PROMETHEUS}"
          },
          "editorMode": "code",
          "expr": "sum(http_server_requests_seconds_count{application=\"wakatime-sync-server\", exception=\"None\"}) by (uri)",
          "legendFormat": "__auto",
          "range": true,
          "refId": "A"
        }
      ],
      "title": "wakatime-sync接口请求次数",
      "type": "timeseries"
    },
    {
      "datasource": {
        "type": "prometheus",
        "uid": "${DS_PROMETHEUS}"
      },
      "fieldConfig": {
        "defaults": {
          "color": {
            "mode": "palette-classic"
          },
          "custom": {
            "axisBorderShow": false,
            "axisCenteredZero": false,
            "axisColorMode": "text",
            "axisLabel": "",
            "axisPlacement": "auto",
            "barAlignment": 0,
            "drawStyle": "points",
            "fillOpacity": 0,
            "gradientMode": "none",
            "hideFrom": {
              "legend": false,
              "tooltip": false,
              "viz": false
            },
            "insertNulls": false,
            "lineInterpolation": "linear",
            "lineWidth": 1,
            "pointSize": 5,
            "scaleDistribution": {
              "type": "linear"
            },
            "showPoints": "auto",
            "spanNulls": false,
            "stacking": {
              "group": "A",
              "mode": "none"
            },
            "thresholdsStyle": {
              "mode": "off"
            }
          },
          "mappings": [],
          "thresholds": {
            "mode": "absolute",
            "steps": [
              {
                "color": "green",
                "value": null
              },
              {
                "color": "red",
                "value": 80
              }
            ]
          }
        },
        "overrides": []
      },
      "gridPos": {
        "h": 8,
        "w": 12,
        "x": 12,
        "y": 1
      },
      "id": 48,
      "options": {
        "legend": {
          "calcs": [],
          "displayMode": "list",
          "placement": "bottom",
          "showLegend": true
        },
        "tooltip": {
          "mode": "single",
          "sort": "none"
        }
      },
      "targets": [
        {
          "datasource": {
            "type": "prometheus",
            "uid": "${DS_PROMETHEUS}"
          },
          "editorMode": "code",
          "expr": "sum by (uri)(irate(http_server_requests_seconds_sum{application=\"wakatime-sync-server\", exception=\"None\"}[1m]))/sum by (uri)(irate(http_server_requests_seconds_count{application=\"wakatime-sync-server\", exception=\"None\"}[1m])) * 1000",
          "legendFormat": "__auto",
          "range": true,
          "refId": "A"
        }
      ],
      "title": "wakatime-sync接口请求耗时(ms)",
      "type": "timeseries"
    },
    {
      "datasource": {
        "type": "prometheus",
        "uid": "${DS_PROMETHEUS}"
      },
      "fieldConfig": {
        "defaults": {
          "color": {
            "mode": "palette-classic"
          },
          "custom": {
            "axisBorderShow": false,
            "axisCenteredZero": false,
            "axisColorMode": "text",
            "axisLabel": "",
            "axisPlacement": "auto",
            "barAlignment": 0,
            "drawStyle": "line",
            "fillOpacity": 0,
            "gradientMode": "none",
            "hideFrom": {
              "legend": false,
              "tooltip": false,
              "viz": false
            },
            "insertNulls": false,
            "lineInterpolation": "linear",
            "lineWidth": 1,
            "pointSize": 5,
            "scaleDistribution": {
              "type": "linear"
            },
            "showPoints": "auto",
            "spanNulls": false,
            "stacking": {
              "group": "A",
              "mode": "none"
            },
            "thresholdsStyle": {
              "mode": "off"
            }
          },
          "mappings": [],
          "thresholds": {
            "mode": "absolute",
            "steps": [
              {
                "color": "green",
                "value": null
              },
              {
                "color": "red",
                "value": 80
              }
            ]
          }
        },
        "overrides": []
      },
      "gridPos": {
        "h": 8,
        "w": 12,
        "x": 0,
        "y": 9
      },
      "id": 50,
      "options": {
        "legend": {
          "calcs": [],
          "displayMode": "list",
          "placement": "bottom",
          "showLegend": true
        },
        "tooltip": {
          "mode": "single",
          "sort": "none"
        }
      },
      "targets": [
        {
          "datasource": {
            "type": "prometheus",
            "uid": "${DS_PROMETHEUS}"
          },
          "editorMode": "code",
          "expr": "sum by (uri) (idelta(http_server_requests_seconds_count{application=\"wakatime-sync-server\", exception!=\"None\"}[1m]))",
          "legendFormat": "__auto",
          "range": true,
          "refId": "A"
        }
      ],
      "title": "ccm-nt-ip-switch接口请求失败次数",
      "type": "timeseries"
    },
    {
      "collapsed": false,
      "gridPos": {
        "h": 1,
        "w": 24,
        "x": 0,
        "y": 17
      },
      "id": 2,
      "panels": [],
      "title": "Basic Statistics",
      "type": "row"
    },
    {
      "datasource": {
        "type": "prometheus",
        "uid": "${DS_PROMETHEUS}"
      },
      "fieldConfig": {
        "defaults": {
          "color": {
            "mode": "thresholds"
          },
          "mappings": [
            {
              "options": {
                "match": "null",
                "result": {
                  "text": "N/A"
                }
              },
              "type": "special"
            }
          ],
          "thresholds": {
            "mode": "absolute",
            "steps": [
              {
                "color": "green"
              },
              {
                "color": "red",
                "value": 80
              }
            ]
          },
          "unit": "dateTimeAsIso"
        },
        "overrides": []
      },
      "gridPos": {
        "h": 3,
        "w": 4,
        "x": 0,
        "y": 18
      },
      "id": 4,
      "links": [],
      "maxDataPoints": 100,
      "options": {
        "colorMode": "value",
        "graphMode": "none",
        "justifyMode": "auto",
        "orientation": "horizontal",
        "reduceOptions": {
          "calcs": [
            "lastNotNull"
          ],
          "fields": "",
          "values": false
        },
        "textMode": "auto"
      },
      "pluginVersion": "10.2.0",
      "targets": [
        {
          "datasource": {
            "type": "prometheus",
            "uid": "${DS_PROMETHEUS}"
          },
          "editorMode": "code",
          "expr": "process_start_time_seconds{application=\"wakatime-sync-server\", instance=\"192.168.1.17:9090\"} * 1000",
          "format": "time_series",
          "intervalFactor": 2,
          "legendFormat": "{{instance}}",
          "metric": "",
          "range": true,
          "refId": "A",
          "step": 14400
        }
      ],
      "title": "启动时间",
      "type": "stat"
    },
    {
      "datasource": {
        "type": "prometheus",
        "uid": "${DS_PROMETHEUS}"
      },
      "fieldConfig": {
        "defaults": {
          "color": {
            "mode": "thresholds"
          },
          "mappings": [
            {
              "options": {
                "match": "null",
                "result": {
                  "text": "N/A"
                }
              },
              "type": "special"
            }
          ],
          "thresholds": {
            "mode": "absolute",
            "steps": [
              {
                "color": "green"
              }
            ]
          },
          "unit": "none"
        },
        "overrides": []
      },
      "gridPos": {
        "h": 3,
        "w": 4,
        "x": 4,
        "y": 18
      },
      "id": 76,
      "links": [],
      "maxDataPoints": 100,
      "options": {
        "colorMode": "value",
        "graphMode": "none",
        "justifyMode": "auto",
        "orientation": "horizontal",
        "reduceOptions": {
          "calcs": [
            "lastNotNull"
          ],
          "fields": "",
          "values": false
        },
        "textMode": "auto"
      },
      "pluginVersion": "10.2.0",
      "targets": [
        {
          "datasource": {
            "type": "prometheus",
            "uid": "${DS_PROMETHEUS}"
          },
          "editorMode": "code",
          "expr": " sum by(instance)(jvm_memory_used_bytes{application=\"$application\", area=\"heap\"} / 1024 / 1024)",
          "format": "time_series",
          "intervalFactor": 2,
          "legendFormat": "{{instance}}",
          "metric": "",
          "range": true,
          "refId": "A",
          "step": 14400
        }
      ],
      "title": "JVM堆使用大小/M",
      "type": "stat"
    },
    {
      "datasource": {
        "type": "prometheus",
        "uid": "${DS_PROMETHEUS}"
      },
      "fieldConfig": {
        "defaults": {
          "color": {
            "mode": "thresholds"
          },
          "mappings": [
            {
              "options": {
                "match": "null",
                "result": {
                  "text": "N/A"
                }
              },
              "type": "special"
            }
          ],
          "thresholds": {
            "mode": "absolute",
            "steps": [
              {
                "color": "green"
              },
              {
                "color": "red",
                "value": 80
              }
            ]
          },
          "unit": "none"
        },
        "overrides": []
      },
      "gridPos": {
        "h": 3,
        "w": 4,
        "x": 8,
        "y": 18
      },
      "id": 6,
      "links": [],
      "maxDataPoints": 100,
      "options": {
        "colorMode": "value",
        "graphMode": "none",
        "justifyMode": "auto",
        "orientation": "horizontal",
        "reduceOptions": {
          "calcs": [
            "lastNotNull"
          ],
          "fields": "",
          "values": false
        },
        "textMode": "auto"
      },
      "pluginVersion": "10.2.0",
      "targets": [
        {
          "datasource": {
            "type": "prometheus",
            "uid": "${DS_PROMETHEUS}"
          },
          "editorMode": "code",
          "expr": "system_cpu_count{application=\"${application}\"}",
          "format": "time_series",
          "intervalFactor": 2,
          "legendFormat": "{{instance}}",
          "metric": "",
          "range": true,
          "refId": "A",
          "step": 14400
        }
      ],
      "title": "Node CPU核心数",
      "type": "stat"
    },
    {
      "aliasColors": {},
      "bars": false,
      "dashLength": 10,
      "dashes": false,
      "datasource": {
        "type": "prometheus",
        "uid": "${DS_PROMETHEUS}"
      },
      "fieldConfig": {
        "defaults": {
          "links": []
        },
        "overrides": []
      },
      "fill": 1,
      "fillGradient": 0,
      "gridPos": {
        "h": 6,
        "w": 12,
        "x": 12,
        "y": 18
      },
      "hiddenSeries": false,
      "id": 22,
      "legend": {
        "avg": false,
        "current": false,
        "max": false,
        "min": false,
        "show": true,
        "total": false,
        "values": false
      },
      "lines": true,
      "linewidth": 1,
      "links": [],
      "nullPointMode": "null",
      "options": {
        "alertThreshold": true
      },
      "percentage": false,
      "pluginVersion": "10.2.0",
      "pointradius": 5,
      "points": false,
      "renderer": "flot",
      "seriesOverrides": [],
      "spaceLength": 10,
      "stack": false,
      "steppedLine": false,
      "targets": [
        {
          "datasource": {
            "type": "prometheus",
            "uid": "${DS_PROMETHEUS}"
          },
          "editorMode": "code",
          "expr": "irate(jvm_gc_memory_allocated_bytes_total{instance=\"$instance\", application=\"$application\"}[5m])",
          "format": "time_series",
          "intervalFactor": 1,
          "legendFormat": "allocated",
          "range": true,
          "refId": "A"
        },
        {
          "datasource": {
            "type": "prometheus",
            "uid": "${DS_PROMETHEUS}"
          },
          "editorMode": "code",
          "expr": "irate(jvm_gc_memory_promoted_bytes_total{instance=\"$instance\", application=\"$application\"}[5m])",
          "format": "time_series",
          "intervalFactor": 1,
          "legendFormat": "promoted",
          "range": true,
          "refId": "B"
        }
      ],
      "thresholds": [],
      "timeRegions": [],
      "title": "Memory Allocate/Promote",
      "tooltip": {
        "shared": true,
        "sort": 0,
        "value_type": "individual"
      },
      "type": "graph",
      "xaxis": {
        "mode": "time",
        "show": true,
        "values": []
      },
      "yaxes": [
        {
          "format": "bytes",
          "logBase": 1,
          "show": true
        },
        {
          "format": "short",
          "logBase": 1,
          "show": true
        }
      ],
      "yaxis": {
        "align": false
      }
    },
    {
      "datasource": {
        "type": "prometheus",
        "uid": "${DS_PROMETHEUS}"
      },
      "fieldConfig": {
        "defaults": {
          "color": {
            "mode": "thresholds"
          },
          "mappings": [
            {
              "options": {
                "match": "null",
                "result": {
                  "text": "N/A"
                }
              },
              "type": "special"
            }
          ],
          "thresholds": {
            "mode": "absolute",
            "steps": [
              {
                "color": "green"
              }
            ]
          },
          "unit": "none"
        },
        "overrides": []
      },
      "gridPos": {
        "h": 3,
        "w": 4,
        "x": 0,
        "y": 21
      },
      "id": 10,
      "links": [],
      "maxDataPoints": 100,
      "options": {
        "colorMode": "value",
        "graphMode": "none",
        "justifyMode": "auto",
        "orientation": "horizontal",
        "reduceOptions": {
          "calcs": [
            "lastNotNull"
          ],
          "fields": "",
          "values": false
        },
        "textMode": "auto"
      },
      "pluginVersion": "10.2.0",
      "targets": [
        {
          "datasource": {
            "type": "prometheus",
            "uid": "${DS_PROMETHEUS}"
          },
          "editorMode": "code",
          "expr": " sum by(instance)(jvm_memory_max_bytes{application=\"$application\", instance=\"$instance\", area=\"heap\"} / 1024 / 1024)",
          "format": "time_series",
          "intervalFactor": 2,
          "legendFormat": "{{instance}}",
          "metric": "",
          "range": true,
          "refId": "A",
          "step": 14400
        }
      ],
      "title": "JVM堆大小/M",
      "type": "stat"
    },
    {
      "datasource": {
        "type": "prometheus",
        "uid": "${DS_PROMETHEUS}"
      },
      "fieldConfig": {
        "defaults": {
          "color": {
            "mode": "thresholds"
          },
          "mappings": [
            {
              "options": {
                "match": "null",
                "result": {
                  "text": "N/A"
                }
              },
              "type": "special"
            }
          ],
          "thresholds": {
            "mode": "absolute",
            "steps": [
              {
                "color": "green"
              }
            ]
          },
          "unit": "none"
        },
        "overrides": []
      },
      "gridPos": {
        "h": 3,
        "w": 4,
        "x": 4,
        "y": 21
      },
      "id": 74,
      "links": [],
      "maxDataPoints": 100,
      "options": {
        "colorMode": "value",
        "graphMode": "none",
        "justifyMode": "auto",
        "orientation": "horizontal",
        "reduceOptions": {
          "calcs": [
            "lastNotNull"
          ],
          "fields": "",
          "values": false
        },
        "textMode": "auto"
      },
      "pluginVersion": "10.2.0",
      "targets": [
        {
          "datasource": {
            "type": "prometheus",
            "uid": "${DS_PROMETHEUS}"
          },
          "editorMode": "code",
          "expr": " sum by(instance)(jvm_memory_used_bytes{application=\"$application\", area=\"nonheap\"} / 1024 / 1024)",
          "format": "time_series",
          "intervalFactor": 2,
          "legendFormat": "{{instance}}",
          "metric": "",
          "range": true,
          "refId": "A",
          "step": 14400
        }
      ],
      "title": "JVM非堆使用大小/M",
      "type": "stat"
    },
    {
      "datasource": {
        "type": "prometheus",
        "uid": "${DS_PROMETHEUS}"
      },
      "fieldConfig": {
        "defaults": {
          "color": {
            "mode": "thresholds"
          },
          "mappings": [
            {
              "options": {
                "match": "null",
                "result": {
                  "text": "N/A"
                }
              },
              "type": "special"
            }
          ],
          "thresholds": {
            "mode": "absolute",
            "steps": [
              {
                "color": "green"
              },
              {
                "color": "red",
                "value": 80
              }
            ]
          },
          "unit": "string"
        },
        "overrides": []
      },
      "gridPos": {
        "h": 3,
        "w": 4,
        "x": 8,
        "y": 21
      },
      "id": 8,
      "links": [],
      "maxDataPoints": 100,
      "options": {
        "colorMode": "value",
        "graphMode": "none",
        "justifyMode": "auto",
        "orientation": "horizontal",
        "reduceOptions": {
          "calcs": [
            "lastNotNull"
          ],
          "fields": "",
          "values": false
        },
        "textMode": "auto"
      },
      "pluginVersion": "10.2.0",
      "targets": [
        {
          "datasource": {
            "type": "prometheus",
            "uid": "${DS_PROMETHEUS}"
          },
          "editorMode": "code",
          "exemplar": false,
          "expr": "round(process_cpu_usage{application=\"$application\"}, 0.0001) ",
          "format": "time_series",
          "instant": false,
          "interval": "",
          "intervalFactor": 2,
          "legendFormat": "{{instance}}",
          "metric": "",
          "range": true,
          "refId": "A",
          "step": 14400
        }
      ],
      "title": "CPU使用核心数",
      "type": "stat"
    },
    {
      "datasource": {
        "type": "prometheus",
        "uid": "${DS_PROMETHEUS}"
      },
      "fieldConfig": {
        "defaults": {
          "color": {
            "mode": "thresholds"
          },
          "decimals": 1,
          "mappings": [
            {
              "options": {
                "match": "null",
                "result": {
                  "text": "N/A"
                }
              },
              "type": "special"
            }
          ],
          "max": 100,
          "min": 0,
          "thresholds": {
            "mode": "absolute",
            "steps": [
              {
                "color": "rgba(50, 172, 45, 0.97)"
              },
              {
                "color": "rgba(237, 129, 40, 0.89)",
                "value": 70
              },
              {
                "color": "rgba(245, 54, 54, 0.9)",
                "value": 90
              }
            ]
          },
          "unit": "percent"
        },
        "overrides": []
      },
      "gridPos": {
        "h": 7,
        "w": 4,
        "x": 0,
        "y": 24
      },
      "id": 16,
      "links": [],
      "maxDataPoints": 100,
      "options": {
        "minVizHeight": 75,
        "minVizWidth": 75,
        "orientation": "vertical",
        "reduceOptions": {
          "calcs": [
            "lastNotNull"
          ],
          "fields": "",
          "values": false
        },
        "showThresholdLabels": false,
        "showThresholdMarkers": true
      },
      "pluginVersion": "10.2.0",
      "targets": [
        {
          "datasource": {
            "type": "prometheus",
            "uid": "${DS_PROMETHEUS}"
          },
          "editorMode": "code",
          "expr": "sum by(instance)(jvm_memory_used_bytes{application=\"$application\", instance=\"$instance\", area=\"heap\"})*100/sum by(instance)(jvm_memory_max_bytes{application=\"$application\", instance=\"$instance\", area=\"heap\"})",
          "format": "time_series",
          "intervalFactor": 1,
          "legendFormat": "{{instance}}",
          "range": true,
          "refId": "A",
          "step": 14400
        }
      ],
      "title": "JVM堆使用率",
      "type": "gauge"
    },
    {
      "datasource": {
        "type": "prometheus",
        "uid": "${DS_PROMETHEUS}"
      },
      "fieldConfig": {
        "defaults": {
          "color": {
            "mode": "thresholds"
          },
          "decimals": 1,
          "mappings": [
            {
              "options": {
                "match": "null",
                "result": {
                  "text": "N/A"
                }
              },
              "type": "special"
            },
            {
              "options": {
                "from": -1e+32,
                "result": {
                  "text": "N/A"
                },
                "to": 0
              },
              "type": "range"
            }
          ],
          "max": 100,
          "min": 0,
          "thresholds": {
            "mode": "absolute",
            "steps": [
              {
                "color": "rgba(50, 172, 45, 0.97)"
              },
              {
                "color": "rgba(237, 129, 40, 0.89)",
                "value": 70
              },
              {
                "color": "rgba(245, 54, 54, 0.9)",
                "value": 90
              }
            ]
          },
          "unit": "percent"
        },
        "overrides": []
      },
      "gridPos": {
        "h": 7,
        "w": 4,
        "x": 4,
        "y": 24
      },
      "id": 18,
      "links": [],
      "maxDataPoints": 100,
      "options": {
        "minVizHeight": 75,
        "minVizWidth": 75,
        "orientation": "vertical",
        "reduceOptions": {
          "calcs": [
            "lastNotNull"
          ],
          "fields": "",
          "values": false
        },
        "showThresholdLabels": false,
        "showThresholdMarkers": true
      },
      "pluginVersion": "10.2.0",
      "targets": [
        {
          "datasource": {
            "type": "prometheus",
            "uid": "${DS_PROMETHEUS}"
          },
          "editorMode": "code",
          "expr": "sum by(instance)(jvm_memory_used_bytes{application=\"$application\", instance=\"$instance\", area=\"nonheap\"})*100/sum by(instance)(jvm_memory_max_bytes{application=\"$application\", instance=\"$instance\", area=\"nonheap\"})",
          "format": "time_series",
          "intervalFactor": 2,
          "legendFormat": "{{instanct}}",
          "range": true,
          "refId": "A",
          "step": 14400
        }
      ],
      "title": "非堆内存使用率",
      "type": "gauge"
    },
    {
      "datasource": {
        "type": "prometheus",
        "uid": "${DS_PROMETHEUS}"
      },
      "fieldConfig": {
        "defaults": {
          "color": {
            "mode": "thresholds"
          },
          "decimals": 1,
          "mappings": [
            {
              "options": {
                "match": "null",
                "result": {
                  "text": "N/A"
                }
              },
              "type": "special"
            }
          ],
          "max": 100,
          "min": 0,
          "thresholds": {
            "mode": "absolute",
            "steps": [
              {
                "color": "rgba(50, 172, 45, 0.97)"
              },
              {
                "color": "rgba(237, 129, 40, 0.89)",
                "value": 70
              },
              {
                "color": "rgba(245, 54, 54, 0.9)",
                "value": 90
              }
            ]
          },
          "unit": "percent"
        },
        "overrides": []
      },
      "gridPos": {
        "h": 7,
        "w": 4,
        "x": 8,
        "y": 24
      },
      "id": 12,
      "links": [],
      "maxDataPoints": 100,
      "options": {
        "minVizHeight": 75,
        "minVizWidth": 75,
        "orientation": "vertical",
        "reduceOptions": {
          "calcs": [
            "lastNotNull"
          ],
          "fields": "",
          "values": false
        },
        "showThresholdLabels": false,
        "showThresholdMarkers": true
      },
      "pluginVersion": "10.2.0",
      "targets": [
        {
          "datasource": {
            "type": "prometheus",
            "uid": "${DS_PROMETHEUS}"
          },
          "editorMode": "code",
          "expr": "process_cpu_usage{application=\"$application\", instance=\"$instance\"} * 100",
          "format": "time_series",
          "intervalFactor": 1,
          "legendFormat": "{{instance}}",
          "range": true,
          "refId": "A",
          "step": 14400
        }
      ],
      "title": "CPU使用率",
      "type": "gauge"
    },
    {
      "aliasColors": {},
      "bars": false,
      "dashLength": 10,
      "dashes": false,
      "datasource": {
        "type": "prometheus",
        "uid": "${DS_PROMETHEUS}"
      },
      "fill": 1,
      "fillGradient": 0,
      "gridPos": {
        "h": 7,
        "w": 12,
        "x": 12,
        "y": 24
      },
      "hiddenSeries": false,
      "id": 52,
      "legend": {
        "alignAsTable": true,
        "avg": true,
        "current": true,
        "max": true,
        "min": true,
        "show": true,
        "total": false,
        "values": true
      },
      "lines": true,
      "linewidth": 1,
      "links": [],
      "nullPointMode": "null",
      "options": {
        "alertThreshold": true
      },
      "percentage": false,
      "pluginVersion": "10.2.0",
      "pointradius": 5,
      "points": false,
      "renderer": "flot",
      "seriesOverrides": [],
      "spaceLength": 10,
      "stack": false,
      "steppedLine": false,
      "targets": [
        {
          "datasource": {
            "type": "prometheus",
            "uid": "${DS_PROMETHEUS}"
          },
          "editorMode": "code",
          "expr": "process_cpu_usage{application=\"${application}\"}",
          "hide": false,
          "instant": false,
          "legendFormat": "__auto",
          "range": true,
          "refId": "A"
        }
      ],
      "thresholds": [],
      "timeRegions": [],
      "title": "CPU 使用情况-核",
      "tooltip": {
        "shared": true,
        "sort": 0,
        "value_type": "individual"
      },
      "type": "graph",
      "xaxis": {
        "mode": "time",
        "show": true,
        "values": []
      },
      "yaxes": [
        {
          "$$hashKey": "object:268",
          "format": "short",
          "logBase": 1,
          "show": true
        },
        {
          "$$hashKey": "object:269",
          "format": "short",
          "logBase": 1,
          "show": true
        }
      ],
      "yaxis": {
        "align": false
      }
    },
    {
      "collapsed": true,
      "gridPos": {
        "h": 1,
        "w": 24,
        "x": 0,
        "y": 31
      },
      "id": 56,
      "panels": [
        {
          "aliasColors": {},
          "bars": false,
          "dashLength": 10,
          "dashes": false,
          "datasource": {
            "type": "prometheus",
            "uid": "${DS_PROMETHEUS}"
          },
          "fill": 1,
          "fillGradient": 0,
          "gridPos": {
            "h": 8,
            "w": 12,
            "x": 0,
            "y": 32
          },
          "hiddenSeries": false,
          "id": 54,
          "legend": {
            "alignAsTable": true,
            "avg": true,
            "current": true,
            "max": true,
            "min": true,
            "show": true,
            "total": false,
            "values": true
          },
          "lines": true,
          "linewidth": 1,
          "links": [],
          "nullPointMode": "null",
          "options": {
            "alertThreshold": true
          },
          "percentage": false,
          "pluginVersion": "10.2.0",
          "pointradius": 5,
          "points": false,
          "renderer": "flot",
          "repeat": "memory_pool_heap",
          "repeatDirection": "v",
          "seriesOverrides": [],
          "spaceLength": 10,
          "stack": false,
          "steppedLine": false,
          "targets": [
            {
              "datasource": {
                "type": "prometheus",
                "uid": "${DS_PROMETHEUS}"
              },
              "expr": "jvm_memory_used_bytes{instance=\"$instance\", application=\"$application\", id=\"$memory_pool_heap\"}",
              "format": "time_series",
              "intervalFactor": 1,
              "legendFormat": "Used",
              "refId": "C"
            },
            {
              "datasource": {
                "type": "prometheus",
                "uid": "${DS_PROMETHEUS}"
              },
              "expr": "jvm_memory_committed_bytes{instance=\"$instance\", application=\"$application\", id=\"$memory_pool_heap\"}",
              "format": "time_series",
              "intervalFactor": 1,
              "legendFormat": "Commited",
              "refId": "A"
            },
            {
              "datasource": {
                "type": "prometheus",
                "uid": "${DS_PROMETHEUS}"
              },
              "expr": "jvm_memory_max_bytes{instance=\"$instance\", application=\"$application\", id=\"$memory_pool_heap\"}",
              "format": "time_series",
              "intervalFactor": 1,
              "legendFormat": "Max",
              "refId": "B"
            }
          ],
          "thresholds": [],
          "timeRegions": [],
          "title": "$memory_pool_heap (heap)",
          "tooltip": {
            "shared": true,
            "sort": 0,
            "value_type": "individual"
          },
          "type": "graph",
          "xaxis": {
            "mode": "time",
            "show": true,
            "values": []
          },
          "yaxes": [
            {
              "format": "bytes",
              "logBase": 1,
              "show": true
            },
            {
              "format": "short",
              "logBase": 1,
              "show": true
            }
          ],
          "yaxis": {
            "align": false
          }
        },
        {
          "aliasColors": {},
          "bars": false,
          "dashLength": 10,
          "dashes": false,
          "datasource": {
            "type": "prometheus",
            "uid": "${DS_PROMETHEUS}"
          },
          "description": "堆内存的使用",
          "fill": 1,
          "fillGradient": 0,
          "gridPos": {
            "h": 8,
            "w": 12,
            "x": 12,
            "y": 32
          },
          "hiddenSeries": false,
          "id": 60,
          "legend": {
            "alignAsTable": true,
            "avg": true,
            "current": true,
            "max": true,
            "min": true,
            "show": true,
            "total": false,
            "values": true
          },
          "lines": true,
          "linewidth": 1,
          "links": [],
          "nullPointMode": "null",
          "options": {
            "alertThreshold": true
          },
          "percentage": false,
          "pluginVersion": "10.2.0",
          "pointradius": 5,
          "points": false,
          "renderer": "flot",
          "repeat": "memory_pool_nonheap",
          "repeatDirection": "v",
          "seriesOverrides": [],
          "spaceLength": 10,
          "stack": false,
          "steppedLine": false,
          "targets": [
            {
              "datasource": {
                "type": "prometheus",
                "uid": "${DS_PROMETHEUS}"
              },
              "editorMode": "code",
              "expr": "jvm_memory_used_bytes{instance=\"$instance\", application=\"$application\", id=\"$memory_pool_nonheap\"}",
              "format": "time_series",
              "intervalFactor": 1,
              "legendFormat": "Used",
              "range": true,
              "refId": "C"
            },
            {
              "datasource": {
                "type": "prometheus",
                "uid": "${DS_PROMETHEUS}"
              },
              "expr": "jvm_memory_committed_bytes{instance=\"$instance\", application=\"$application\", id=\"$memory_pool_nonheap\"}",
              "format": "time_series",
              "intervalFactor": 1,
              "legendFormat": "Commited",
              "refId": "A"
            },
            {
              "datasource": {
                "type": "prometheus",
                "uid": "${DS_PROMETHEUS}"
              },
              "expr": "jvm_memory_max_bytes{instance=\"$instance\", application=\"$application\", id=\"$memory_pool_nonheap\"}",
              "format": "time_series",
              "intervalFactor": 1,
              "legendFormat": "Max",
              "refId": "B"
            }
          ],
          "thresholds": [],
          "timeRegions": [],
          "title": "memory_pool_nonheap (non-heap)",
          "tooltip": {
            "shared": true,
            "sort": 0,
            "value_type": "individual"
          },
          "type": "graph",
          "xaxis": {
            "mode": "time",
            "show": true,
            "values": []
          },
          "yaxes": [
            {
              "$$hashKey": "object:17495",
              "format": "bytes",
              "logBase": 1,
              "show": true
            },
            {
              "$$hashKey": "object:17496",
              "format": "short",
              "logBase": 1,
              "show": true
            }
          ],
          "yaxis": {
            "align": false
          }
        },
        {
          "aliasColors": {},
          "bars": false,
          "dashLength": 10,
          "dashes": false,
          "datasource": {
            "type": "prometheus",
            "uid": "${DS_PROMETHEUS}"
          },
          "fill": 1,
          "fillGradient": 0,
          "gridPos": {
            "h": 8,
            "w": 12,
            "x": 0,
            "y": 40
          },
          "hiddenSeries": false,
          "id": 58,
          "legend": {
            "avg": false,
            "current": false,
            "max": false,
            "min": false,
            "show": true,
            "total": false,
            "values": false
          },
          "lines": true,
          "linewidth": 1,
          "links": [],
          "nullPointMode": "null",
          "options": {
            "alertThreshold": true
          },
          "percentage": false,
          "pluginVersion": "10.2.0",
          "pointradius": 5,
          "points": false,
          "renderer": "flot",
          "seriesOverrides": [],
          "spaceLength": 10,
          "stack": false,
          "steppedLine": false,
          "targets": [
            {
              "datasource": {
                "type": "prometheus",
                "uid": "${DS_PROMETHEUS}"
              },
              "exemplar": true,
              "expr": "irate(jvm_classes_unloaded_classes_total{instance=\"$instance\", application=\"$application\"}[5m])",
              "format": "time_series",
              "interval": "",
              "intervalFactor": 1,
              "legendFormat": "Classes Unloaded",
              "refId": "A"
            }
          ],
          "thresholds": [],
          "timeRegions": [],
          "title": "Classes Unloaded",
          "tooltip": {
            "shared": true,
            "sort": 0,
            "value_type": "individual"
          },
          "type": "graph",
          "xaxis": {
            "mode": "time",
            "show": true,
            "values": []
          },
          "yaxes": [
            {
              "format": "short",
              "logBase": 1,
              "show": true
            },
            {
              "format": "short",
              "logBase": 1,
              "show": true
            }
          ],
          "yaxis": {
            "align": false
          }
        },
        {
          "aliasColors": {},
          "bars": false,
          "dashLength": 10,
          "dashes": false,
          "datasource": {
            "type": "prometheus",
            "uid": "${DS_PROMETHEUS}"
          },
          "fill": 1,
          "fillGradient": 0,
          "gridPos": {
            "h": 8,
            "w": 12,
            "x": 12,
            "y": 40
          },
          "hiddenSeries": false,
          "id": 62,
          "legend": {
            "avg": false,
            "current": false,
            "max": false,
            "min": false,
            "show": true,
            "total": false,
            "values": false
          },
          "lines": true,
          "linewidth": 1,
          "links": [],
          "nullPointMode": "null",
          "options": {
            "alertThreshold": true
          },
          "percentage": false,
          "pluginVersion": "10.2.0",
          "pointradius": 5,
          "points": false,
          "renderer": "flot",
          "seriesOverrides": [],
          "spaceLength": 10,
          "stack": false,
          "steppedLine": false,
          "targets": [
            {
              "datasource": {
                "type": "prometheus",
                "uid": "${DS_PROMETHEUS}"
              },
              "expr": "jvm_buffer_memory_used_bytes{instance=\"$instance\", application=\"$application\", id=\"mapped\"}",
              "format": "time_series",
              "intervalFactor": 1,
              "legendFormat": "Used Bytes",
              "refId": "A"
            },
            {
              "datasource": {
                "type": "prometheus",
                "uid": "${DS_PROMETHEUS}"
              },
              "expr": "jvm_buffer_total_capacity_bytes{instance=\"$instance\", application=\"$application\", id=\"mapped\"}",
              "format": "time_series",
              "intervalFactor": 1,
              "legendFormat": "Capacity Bytes",
              "refId": "B"
            }
          ],
          "thresholds": [],
          "timeRegions": [],
          "title": "Mapped Buffers",
          "tooltip": {
            "shared": true,
            "sort": 0,
            "value_type": "individual"
          },
          "type": "graph",
          "xaxis": {
            "mode": "time",
            "show": true,
            "values": []
          },
          "yaxes": [
            {
              "format": "short",
              "logBase": 1,
              "show": true
            },
            {
              "format": "short",
              "logBase": 1,
              "show": true
            }
          ],
          "yaxis": {
            "align": false
          }
        },
        {
          "aliasColors": {},
          "bars": false,
          "dashLength": 10,
          "dashes": false,
          "datasource": {
            "type": "prometheus",
            "uid": "${DS_PROMETHEUS}"
          },
          "decimals": 0,
          "fill": 1,
          "fillGradient": 0,
          "gridPos": {
            "h": 8,
            "w": 12,
            "x": 0,
            "y": 48
          },
          "hiddenSeries": false,
          "id": 64,
          "legend": {
            "alignAsTable": true,
            "avg": true,
            "current": true,
            "max": true,
            "min": true,
            "show": true,
            "total": false,
            "values": true
          },
          "lines": true,
          "linewidth": 1,
          "links": [],
          "nullPointMode": "null",
          "options": {
            "alertThreshold": true
          },
          "percentage": false,
          "pluginVersion": "10.2.0",
          "pointradius": 5,
          "points": false,
          "renderer": "flot",
          "seriesOverrides": [],
          "spaceLength": 10,
          "stack": false,
          "steppedLine": false,
          "targets": [
            {
              "datasource": {
                "type": "prometheus",
                "uid": "${DS_PROMETHEUS}"
              },
              "editorMode": "code",
              "exemplar": true,
              "expr": "jvm_classes_loaded_classes{instance=\"$instance\", application=\"$application\"}",
              "format": "time_series",
              "interval": "",
              "intervalFactor": 1,
              "legendFormat": "Classes Loaded",
              "range": true,
              "refId": "A"
            }
          ],
          "thresholds": [],
          "timeRegions": [],
          "title": "Classes Loaded",
          "tooltip": {
            "shared": true,
            "sort": 0,
            "value_type": "individual"
          },
          "type": "graph",
          "xaxis": {
            "mode": "time",
            "show": true,
            "values": []
          },
          "yaxes": [
            {
              "$$hashKey": "object:101",
              "decimals": 0,
              "format": "locale",
              "label": "",
              "logBase": 1,
              "show": true
            },
            {
              "$$hashKey": "object:102",
              "format": "short",
              "logBase": 1,
              "show": true
            }
          ],
          "yaxis": {
            "align": false
          }
        },
        {
          "aliasColors": {},
          "bars": false,
          "dashLength": 10,
          "dashes": false,
          "datasource": {
            "type": "prometheus",
            "uid": "${DS_PROMETHEUS}"
          },
          "fill": 1,
          "fillGradient": 0,
          "gridPos": {
            "h": 8,
            "w": 12,
            "x": 12,
            "y": 48
          },
          "hiddenSeries": false,
          "id": 66,
          "legend": {
            "avg": false,
            "current": false,
            "max": false,
            "min": false,
            "show": true,
            "total": false,
            "values": false
          },
          "lines": true,
          "linewidth": 1,
          "links": [],
          "nullPointMode": "null",
          "options": {
            "alertThreshold": true
          },
          "percentage": false,
          "pluginVersion": "10.2.0",
          "pointradius": 5,
          "points": false,
          "renderer": "flot",
          "seriesOverrides": [],
          "spaceLength": 10,
          "stack": false,
          "steppedLine": false,
          "targets": [
            {
              "datasource": {
                "type": "prometheus",
                "uid": "${DS_PROMETHEUS}"
              },
              "editorMode": "code",
              "expr": "irate(jvm_gc_memory_allocated_bytes_total{instance=\"$instance\", application=\"$application\"}[5m])",
              "format": "time_series",
              "intervalFactor": 1,
              "legendFormat": "allocated",
              "range": true,
              "refId": "A"
            },
            {
              "datasource": {
                "type": "prometheus",
                "uid": "${DS_PROMETHEUS}"
              },
              "expr": "irate(jvm_gc_memory_promoted_bytes_total{instance=\"$instance\", application=\"$application\"}[5m])",
              "format": "time_series",
              "intervalFactor": 1,
              "legendFormat": "promoted",
              "refId": "B"
            }
          ],
          "thresholds": [],
          "timeRegions": [],
          "title": "Memory Allocate/Promote",
          "tooltip": {
            "shared": true,
            "sort": 0,
            "value_type": "individual"
          },
          "type": "graph",
          "xaxis": {
            "mode": "time",
            "show": true,
            "values": []
          },
          "yaxes": [
            {
              "format": "bytes",
              "logBase": 1,
              "show": true
            },
            {
              "format": "short",
              "logBase": 1,
              "show": true
            }
          ],
          "yaxis": {
            "align": false
          }
        },
        {
          "aliasColors": {},
          "bars": false,
          "dashLength": 10,
          "dashes": false,
          "datasource": {
            "type": "prometheus",
            "uid": "${DS_PROMETHEUS}"
          },
          "fill": 1,
          "fillGradient": 0,
          "gridPos": {
            "h": 8,
            "w": 12,
            "x": 0,
            "y": 56
          },
          "hiddenSeries": false,
          "id": 68,
          "legend": {
            "avg": false,
            "current": false,
            "max": false,
            "min": false,
            "show": true,
            "total": false,
            "values": false
          },
          "lines": true,
          "linewidth": 1,
          "links": [],
          "nullPointMode": "null",
          "options": {
            "alertThreshold": true
          },
          "percentage": false,
          "pluginVersion": "10.2.0",
          "pointradius": 5,
          "points": false,
          "renderer": "flot",
          "seriesOverrides": [],
          "spaceLength": 10,
          "stack": false,
          "steppedLine": false,
          "targets": [
            {
              "datasource": {
                "type": "prometheus",
                "uid": "${DS_PROMETHEUS}"
              },
              "editorMode": "code",
              "expr": "jvm_buffer_memory_used_bytes{instance=\"$instance\", application=\"$application\", id=\"direct\"}",
              "format": "time_series",
              "intervalFactor": 1,
              "legendFormat": "Used Bytes",
              "range": true,
              "refId": "A"
            },
            {
              "datasource": {
                "type": "prometheus",
                "uid": "${DS_PROMETHEUS}"
              },
              "expr": "jvm_buffer_total_capacity_bytes{instance=\"$instance\", application=\"$application\", id=\"direct\"}",
              "format": "time_series",
              "intervalFactor": 1,
              "legendFormat": "Capacity Bytes",
              "refId": "B"
            }
          ],
          "thresholds": [],
          "timeRegions": [],
          "title": "Direct Buffers",
          "tooltip": {
            "shared": true,
            "sort": 0,
            "value_type": "individual"
          },
          "type": "graph",
          "xaxis": {
            "mode": "time",
            "show": true,
            "values": []
          },
          "yaxes": [
            {
              "format": "short",
              "logBase": 1,
              "show": true
            },
            {
              "format": "short",
              "logBase": 1,
              "show": true
            }
          ],
          "yaxis": {
            "align": false
          }
        },
        {
          "aliasColors": {},
          "bars": false,
          "dashLength": 10,
          "dashes": false,
          "datasource": {
            "type": "prometheus",
            "uid": "${DS_PROMETHEUS}"
          },
          "fill": 1,
          "fillGradient": 0,
          "gridPos": {
            "h": 8,
            "w": 12,
            "x": 12,
            "y": 56
          },
          "hiddenSeries": false,
          "id": 70,
          "legend": {
            "alignAsTable": true,
            "avg": true,
            "current": true,
            "max": true,
            "min": true,
            "show": true,
            "total": false,
            "values": true
          },
          "lines": true,
          "linewidth": 1,
          "links": [],
          "nullPointMode": "null",
          "options": {
            "alertThreshold": true
          },
          "percentage": false,
          "pluginVersion": "10.2.0",
          "pointradius": 5,
          "points": false,
          "renderer": "flot",
          "seriesOverrides": [],
          "spaceLength": 10,
          "stack": false,
          "steppedLine": false,
          "targets": [
            {
              "datasource": {
                "type": "prometheus",
                "uid": "${DS_PROMETHEUS}"
              },
              "exemplar": true,
              "expr": "jvm_threads_daemon_threads{instance=\"$instance\", application=\"$application\"}",
              "format": "time_series",
              "interval": "",
              "intervalFactor": 1,
              "legendFormat": "Daemon",
              "refId": "A"
            },
            {
              "datasource": {
                "type": "prometheus",
                "uid": "${DS_PROMETHEUS}"
              },
              "exemplar": true,
              "expr": "jvm_threads_live_threads{instance=\"$instance\", application=\"$application\"}",
              "format": "time_series",
              "interval": "",
              "intervalFactor": 1,
              "legendFormat": "Live",
              "refId": "B"
            },
            {
              "datasource": {
                "type": "prometheus",
                "uid": "${DS_PROMETHEUS}"
              },
              "exemplar": true,
              "expr": "jvm_threads_peak_threads{instance=\"$instance\", application=\"$application\"}",
              "format": "time_series",
              "interval": "",
              "intervalFactor": 1,
              "legendFormat": "Peak",
              "refId": "C"
            }
          ],
          "thresholds": [],
          "timeRegions": [],
          "title": "Threads",
          "tooltip": {
            "shared": true,
            "sort": 0,
            "value_type": "individual"
          },
          "type": "graph",
          "xaxis": {
            "mode": "time",
            "show": true,
            "values": []
          },
          "yaxes": [
            {
              "format": "short",
              "logBase": 1,
              "show": true
            },
            {
              "format": "short",
              "logBase": 1,
              "show": true
            }
          ],
          "yaxis": {
            "align": false
          }
        }
      ],
      "title": "JVM Statistics - Memory",
      "type": "row"
    },
    {
      "collapsed": true,
      "gridPos": {
        "h": 1,
        "w": 24,
        "x": 0,
        "y": 32
      },
      "id": 26,
      "panels": [
        {
          "aliasColors": {},
          "bars": false,
          "dashLength": 10,
          "dashes": false,
          "datasource": {
            "type": "prometheus",
            "uid": "${DS_PROMETHEUS}"
          },
          "fill": 1,
          "fillGradient": 0,
          "gridPos": {
            "h": 10,
            "w": 12,
            "x": 0,
            "y": 65
          },
          "hiddenSeries": false,
          "id": 28,
          "legend": {
            "alignAsTable": true,
            "avg": true,
            "current": false,
            "hideEmpty": true,
            "hideZero": true,
            "max": true,
            "min": true,
            "show": true,
            "total": true,
            "values": true
          },
          "lines": true,
          "linewidth": 1,
          "links": [],
          "nullPointMode": "null",
          "options": {
            "alertThreshold": true
          },
          "percentage": false,
          "pluginVersion": "10.2.0",
          "pointradius": 5,
          "points": false,
          "renderer": "flot",
          "seriesOverrides": [],
          "spaceLength": 10,
          "stack": false,
          "steppedLine": false,
          "targets": [
            {
              "datasource": {
                "type": "prometheus",
                "uid": "${DS_PROMETHEUS}"
              },
              "editorMode": "code",
              "expr": "increase(jvm_gc_pause_seconds_count{instance=\"$instance\", application=\"$application\"}[30s])",
              "format": "time_series",
              "intervalFactor": 1,
              "legendFormat": "{{action}} [{{cause}}]",
              "range": true,
              "refId": "A"
            }
          ],
          "thresholds": [],
          "timeRegions": [],
          "title": "GC Count",
          "tooltip": {
            "shared": true,
            "sort": 0,
            "value_type": "individual"
          },
          "type": "graph",
          "xaxis": {
            "mode": "time",
            "show": true,
            "values": []
          },
          "yaxes": [
            {
              "$$hashKey": "object:113",
              "format": "locale",
              "logBase": 1,
              "show": true
            },
            {
              "$$hashKey": "object:114",
              "format": "short",
              "logBase": 1,
              "show": true
            }
          ],
          "yaxis": {
            "align": false
          }
        },
        {
          "aliasColors": {},
          "bars": false,
          "dashLength": 10,
          "dashes": false,
          "datasource": {
            "type": "prometheus",
            "uid": "${DS_PROMETHEUS}"
          },
          "fill": 1,
          "fillGradient": 0,
          "gridPos": {
            "h": 10,
            "w": 12,
            "x": 12,
            "y": 65
          },
          "hiddenSeries": false,
          "id": 30,
          "legend": {
            "alignAsTable": true,
            "avg": true,
            "current": false,
            "hideEmpty": true,
            "hideZero": true,
            "max": true,
            "min": true,
            "show": true,
            "total": true,
            "values": true
          },
          "lines": true,
          "linewidth": 1,
          "links": [],
          "nullPointMode": "null",
          "options": {
            "alertThreshold": true
          },
          "percentage": false,
          "pluginVersion": "10.2.0",
          "pointradius": 5,
          "points": false,
          "renderer": "flot",
          "seriesOverrides": [],
          "spaceLength": 10,
          "stack": false,
          "steppedLine": false,
          "targets": [
            {
              "datasource": {
                "type": "prometheus",
                "uid": "${DS_PROMETHEUS}"
              },
              "expr": "irate(jvm_gc_pause_seconds_sum{instance=\"$instance\", application=\"$application\"}[5m])",
              "format": "time_series",
              "intervalFactor": 1,
              "legendFormat": "{{action}} [{{cause}}]",
              "refId": "A"
            }
          ],
          "thresholds": [],
          "timeRegions": [],
          "title": "GC Stop the World Duration",
          "tooltip": {
            "shared": true,
            "sort": 0,
            "value_type": "individual"
          },
          "type": "graph",
          "xaxis": {
            "mode": "time",
            "show": true,
            "values": []
          },
          "yaxes": [
            {
              "format": "s",
              "logBase": 1,
              "show": true
            },
            {
              "format": "short",
              "logBase": 1,
              "show": true
            }
          ],
          "yaxis": {
            "align": false
          }
        }
      ],
      "title": "JVM Statistisc - GC",
      "type": "row"
    },
    {
      "collapsed": true,
      "gridPos": {
        "h": 1,
        "w": 24,
        "x": 0,
        "y": 33
      },
      "id": 32,
      "panels": [
        {
          "aliasColors": {},
          "bars": false,
          "dashLength": 10,
          "dashes": false,
          "datasource": {
            "type": "prometheus",
            "uid": "${DS_PROMETHEUS}"
          },
          "fill": 1,
          "fillGradient": 0,
          "gridPos": {
            "h": 7,
            "w": 12,
            "x": 0,
            "y": 66
          },
          "hiddenSeries": false,
          "id": 34,
          "legend": {
            "alignAsTable": true,
            "avg": true,
            "current": true,
            "max": true,
            "min": true,
            "show": true,
            "total": true,
            "values": true
          },
          "lines": true,
          "linewidth": 1,
          "links": [],
          "nullPointMode": "null",
          "options": {
            "alertThreshold": true
          },
          "percentage": false,
          "pluginVersion": "10.2.0",
          "pointradius": 5,
          "points": false,
          "renderer": "flot",
          "seriesOverrides": [],
          "spaceLength": 10,
          "stack": false,
          "steppedLine": false,
          "targets": [
            {
              "alias": "",
              "datasource": {
                "type": "prometheus",
                "uid": "${DS_PROMETHEUS}"
              },
              "exemplar": true,
              "expr": "irate(log4j2_events_total{instance=\"$instance\", application=\"$application\", level=\"info\"}[5m])",
              "format": "time_series",
              "interval": "",
              "intervalFactor": 1,
              "legendFormat": "info",
              "rawSql": "SELECT\n  $__time(time_column),\n  value1\nFROM\n  metric_table\nWHERE\n  $__timeFilter(time_column)\n",
              "refId": "A"
            }
          ],
          "thresholds": [],
          "timeRegions": [],
          "title": "INFO logs",
          "tooltip": {
            "shared": true,
            "sort": 0,
            "value_type": "individual"
          },
          "type": "graph",
          "xaxis": {
            "mode": "time",
            "show": true,
            "values": []
          },
          "yaxes": [
            {
              "$$hashKey": "object:583",
              "format": "none",
              "logBase": 1,
              "show": true
            },
            {
              "$$hashKey": "object:584",
              "format": "short",
              "logBase": 1,
              "show": true
            }
          ],
          "yaxis": {
            "align": false
          }
        },
        {
          "aliasColors": {},
          "bars": false,
          "dashLength": 10,
          "dashes": false,
          "datasource": {
            "type": "prometheus",
            "uid": "${DS_PROMETHEUS}"
          },
          "fill": 1,
          "fillGradient": 0,
          "gridPos": {
            "h": 7,
            "w": 12,
            "x": 12,
            "y": 66
          },
          "hiddenSeries": false,
          "id": 36,
          "legend": {
            "alignAsTable": true,
            "avg": true,
            "current": true,
            "max": true,
            "min": true,
            "show": true,
            "total": true,
            "values": true
          },
          "lines": true,
          "linewidth": 1,
          "links": [],
          "nullPointMode": "null",
          "options": {
            "alertThreshold": true
          },
          "percentage": false,
          "pluginVersion": "10.2.0",
          "pointradius": 5,
          "points": false,
          "renderer": "flot",
          "seriesOverrides": [],
          "spaceLength": 10,
          "stack": false,
          "steppedLine": false,
          "targets": [
            {
              "alias": "",
              "datasource": {
                "type": "prometheus",
                "uid": "${DS_PROMETHEUS}"
              },
              "expr": "irate(log4j2_events_total{instance=\"$instance\", application=\"$application\", level=\"error\"}[5m])",
              "format": "time_series",
              "intervalFactor": 1,
              "legendFormat": "error",
              "rawSql": "SELECT\n  $__time(time_column),\n  value1\nFROM\n  metric_table\nWHERE\n  $__timeFilter(time_column)\n",
              "refId": "A"
            }
          ],
          "thresholds": [],
          "timeRegions": [],
          "title": "ERROR logs",
          "tooltip": {
            "shared": true,
            "sort": 0,
            "value_type": "individual"
          },
          "type": "graph",
          "xaxis": {
            "mode": "time",
            "show": true,
            "values": []
          },
          "yaxes": [
            {
              "format": "none",
              "logBase": 1,
              "show": true
            },
            {
              "format": "short",
              "logBase": 1,
              "show": true
            }
          ],
          "yaxis": {
            "align": false
          }
        },
        {
          "aliasColors": {},
          "bars": false,
          "dashLength": 10,
          "dashes": false,
          "datasource": {
            "type": "prometheus",
            "uid": "${DS_PROMETHEUS}"
          },
          "fill": 1,
          "fillGradient": 0,
          "gridPos": {
            "h": 7,
            "w": 8,
            "x": 0,
            "y": 73
          },
          "hiddenSeries": false,
          "id": 38,
          "legend": {
            "alignAsTable": true,
            "avg": true,
            "current": true,
            "max": true,
            "min": true,
            "show": true,
            "total": true,
            "values": true
          },
          "lines": true,
          "linewidth": 1,
          "links": [],
          "nullPointMode": "null",
          "options": {
            "alertThreshold": true
          },
          "percentage": false,
          "pluginVersion": "10.2.0",
          "pointradius": 5,
          "points": false,
          "renderer": "flot",
          "seriesOverrides": [],
          "spaceLength": 10,
          "stack": false,
          "steppedLine": false,
          "targets": [
            {
              "alias": "",
              "datasource": {
                "type": "prometheus",
                "uid": "${DS_PROMETHEUS}"
              },
              "expr": "irate(log4j2_events_total{instance=\"$instance\", application=\"$application\", level=\"warn\"}[5m])",
              "format": "time_series",
              "intervalFactor": 1,
              "legendFormat": "warn",
              "rawSql": "SELECT\n  $__time(time_column),\n  value1\nFROM\n  metric_table\nWHERE\n  $__timeFilter(time_column)\n",
              "refId": "A"
            }
          ],
          "thresholds": [],
          "timeRegions": [],
          "title": "WARN logs",
          "tooltip": {
            "shared": true,
            "sort": 0,
            "value_type": "individual"
          },
          "type": "graph",
          "xaxis": {
            "mode": "time",
            "show": true,
            "values": []
          },
          "yaxes": [
            {
              "format": "none",
              "logBase": 1,
              "show": true
            },
            {
              "format": "short",
              "logBase": 1,
              "show": true
            }
          ],
          "yaxis": {
            "align": false
          }
        },
        {
          "aliasColors": {},
          "bars": false,
          "dashLength": 10,
          "dashes": false,
          "datasource": {
            "type": "prometheus",
            "uid": "${DS_PROMETHEUS}"
          },
          "fill": 1,
          "fillGradient": 0,
          "gridPos": {
            "h": 7,
            "w": 8,
            "x": 8,
            "y": 73
          },
          "hiddenSeries": false,
          "id": 40,
          "legend": {
            "alignAsTable": true,
            "avg": true,
            "current": true,
            "max": true,
            "min": true,
            "show": true,
            "total": true,
            "values": true
          },
          "lines": true,
          "linewidth": 1,
          "links": [],
          "nullPointMode": "null",
          "options": {
            "alertThreshold": true
          },
          "percentage": false,
          "pluginVersion": "10.2.0",
          "pointradius": 5,
          "points": false,
          "renderer": "flot",
          "seriesOverrides": [],
          "spaceLength": 10,
          "stack": false,
          "steppedLine": false,
          "targets": [
            {
              "alias": "",
              "datasource": {
                "type": "prometheus",
                "uid": "${DS_PROMETHEUS}"
              },
              "expr": "irate(log4j2_events_total{instance=\"$instance\", application=\"$application\", level=\"debug\"}[5m])",
              "format": "time_series",
              "intervalFactor": 1,
              "legendFormat": "debug",
              "rawSql": "SELECT\n  $__time(time_column),\n  value1\nFROM\n  metric_table\nWHERE\n  $__timeFilter(time_column)\n",
              "refId": "A"
            }
          ],
          "thresholds": [],
          "timeRegions": [],
          "title": "DEBUG logs",
          "tooltip": {
            "shared": true,
            "sort": 0,
            "value_type": "individual"
          },
          "type": "graph",
          "xaxis": {
            "mode": "time",
            "show": true,
            "values": []
          },
          "yaxes": [
            {
              "format": "none",
              "logBase": 1,
              "show": true
            },
            {
              "format": "short",
              "logBase": 1,
              "show": true
            }
          ],
          "yaxis": {
            "align": false
          }
        },
        {
          "aliasColors": {},
          "bars": false,
          "dashLength": 10,
          "dashes": false,
          "datasource": {
            "type": "prometheus",
            "uid": "${DS_PROMETHEUS}"
          },
          "fill": 1,
          "fillGradient": 0,
          "gridPos": {
            "h": 7,
            "w": 8,
            "x": 16,
            "y": 73
          },
          "hiddenSeries": false,
          "id": 42,
          "legend": {
            "alignAsTable": true,
            "avg": true,
            "current": true,
            "max": true,
            "min": true,
            "show": true,
            "total": true,
            "values": true
          },
          "lines": true,
          "linewidth": 1,
          "links": [],
          "nullPointMode": "null",
          "options": {
            "alertThreshold": true
          },
          "percentage": false,
          "pluginVersion": "10.2.0",
          "pointradius": 5,
          "points": false,
          "renderer": "flot",
          "seriesOverrides": [],
          "spaceLength": 10,
          "stack": false,
          "steppedLine": false,
          "targets": [
            {
              "alias": "",
              "datasource": {
                "type": "prometheus",
                "uid": "${DS_PROMETHEUS}"
              },
              "expr": "irate(log4j2_events_total{instance=\"$instance\", application=\"$application\", level=\"trace\"}[5m])",
              "format": "time_series",
              "intervalFactor": 1,
              "legendFormat": "trace",
              "rawSql": "SELECT\n  $__time(time_column),\n  value1\nFROM\n  metric_table\nWHERE\n  $__timeFilter(time_column)\n",
              "refId": "A"
            }
          ],
          "thresholds": [],
          "timeRegions": [],
          "title": "TRACE logs",
          "tooltip": {
            "shared": true,
            "sort": 0,
            "value_type": "individual"
          },
          "type": "graph",
          "xaxis": {
            "mode": "time",
            "show": true,
            "values": []
          },
          "yaxes": [
            {
              "format": "none",
              "logBase": 1,
              "show": true
            },
            {
              "format": "short",
              "logBase": 1,
              "show": true
            }
          ],
          "yaxis": {
            "align": false
          }
        }
      ],
      "title": "Log4j2 Statistics",
      "type": "row"
    }
  ],
  "refresh": "",
  "revision": 1,
  "schemaVersion": 38,
  "tags": [],
  "templating": {
    "list": [
      {
        "hide": 2,
        "label": "application",
        "name": "application",
        "query": "${VAR_APPLICATION}",
        "skipUrlSync": false,
        "type": "constant",
        "current": {
          "value": "${VAR_APPLICATION}",
          "text": "${VAR_APPLICATION}",
          "selected": false
        },
        "options": [
          {
            "value": "${VAR_APPLICATION}",
            "text": "${VAR_APPLICATION}",
            "selected": false
          }
        ]
      },
      {
        "description": "",
        "hide": 2,
        "label": "Instance",
        "name": "instance",
        "query": "${VAR_INSTANCE}",
        "skipUrlSync": false,
        "type": "constant",
        "current": {
          "value": "${VAR_INSTANCE}",
          "text": "${VAR_INSTANCE}",
          "selected": false
        },
        "options": [
          {
            "value": "${VAR_INSTANCE}",
            "text": "${VAR_INSTANCE}",
            "selected": false
          }
        ]
      },
      {
        "current": {},
        "datasource": {
          "type": "prometheus",
          "uid": "${DS_PROMETHEUS}"
        },
        "definition": "label_values(jvm_memory_used_bytes{application=\"$application\", instance=\"$instance\", area=\"heap\"},id)",
        "hide": 0,
        "includeAll": false,
        "label": "Memory Pool (heap)",
        "multi": false,
        "name": "memory_pool_heap",
        "options": [],
        "query": {
          "query": "label_values(jvm_memory_used_bytes{application=\"$application\", instance=\"$instance\", area=\"heap\"},id)",
          "refId": "StandardVariableQuery"
        },
        "refresh": 1,
        "regex": "",
        "skipUrlSync": false,
        "sort": 1,
        "type": "query"
      },
      {
        "current": {},
        "datasource": {
          "type": "prometheus",
          "uid": "${DS_PROMETHEUS}"
        },
        "definition": "label_values(jvm_memory_used_bytes{application=\"$application\", instance=\"$instance\", area=\"nonheap\"},id)",
        "hide": 0,
        "includeAll": false,
        "label": "Memory Pool (nonheap)",
        "multi": false,
        "name": "memory_pool_nonheap",
        "options": [],
        "query": {
          "query": "label_values(jvm_memory_used_bytes{application=\"$application\", instance=\"$instance\", area=\"nonheap\"},id)",
          "refId": "StandardVariableQuery"
        },
        "refresh": 1,
        "regex": "",
        "skipUrlSync": false,
        "sort": 0,
        "type": "query"
      }
    ]
  },
  "time": {
    "from": "now-15m",
    "to": "now"
  },
  "timepicker": {},
  "timezone": "",
  "title": "wakatime-sync-server",
  "uid": "ZbLtt5VIk",
  "version": 6,
  "weekStart": ""
}